auth_xjtu/__init__.py
auth_xjtu/authenticator.py
auth_xjtu/core/find_entry.py
auth_xjtu/core/follow_redirects.py
auth_xjtu/core/payload_constructor.py
auth_xjtu-0.2.1.dist-info/licenses/LICENSE
auth_xjtu-0.2.1.dist-info/METADATA
auth_xjtu-0.2.1.dist-info/WHEEL
auth_xjtu-0.2.1.dist-info/top_level.txt
auth_xjtu-0.2.1.dist-info/RECORD
