Metadata-Version: 2.4
Name: auth_xjtu
Version: 0.2.1
Summary: Automated XJTU OpenPlatform OAuth authentication for Python
Author-email: Rouge Lin <rougeLin3877@gmail.com>
License-Expression: MIT
Project-URL: Homepage, https://github.com/rouge3877/Auth.xjtu
Project-URL: Issues, https://github.com/rouge3877/Auth.xjtu/issues
Keywords: xjtu,auth_xjtuoauth,authentication,python
Classifier: Programming Language :: Python :: 3
Classifier: Operating System :: OS Independent
Requires-Python: >=3.9
License-File: LICENSE
Requires-Dist: requests>=2.28.1
Requires-Dist: pycryptodome>=3.15.0
Requires-Dist: beautifulsoup4>=4.13.4
Requires-Dist: pytest==8.4.1
Dynamic: license-file
